haystack_integrations/components/generators/py.typed
haystack_integrations/components/generators/anthropic/__init__.py
haystack_integrations/components/generators/anthropic/generator.py
haystack_integrations/components/generators/anthropic/chat/__init__.py
haystack_integrations/components/generators/anthropic/chat/chat_generator.py
haystack_integrations/components/generators/anthropic/chat/utils.py
haystack_integrations/components/generators/anthropic/chat/vertex_chat_generator.py
anthropic_haystack-5.1.0.dist-info/METADATA
anthropic_haystack-5.1.0.dist-info/WHEEL
anthropic_haystack-5.1.0.dist-info/licenses/LICENSE.txt
anthropic_haystack-5.1.0.dist-info/RECORD
